{"signal":[{"name":"clk250","wave":"P...............................","periods":32},{},["PCIe App 256-bit Payload",{"name":"wren","wave":"0..............................."},{"name":"end_of_event","wave":"0..............................."},{"name":"data[255:0]","wave":"x...............................","data":[]},{"name":"slot0","wave":"x...............................","data":[]},{"name":"slot1","wave":"x...............................","data":[]},{"name":"slot2","wave":"x...............................","data":[]},{"name":"slot3","wave":"x...............................","data":[]}]],"config":{"hscale":4},"head":{"text":"PCIe app payload chunk 235/309: cycles 11374..11405","tick":0},"foot":{"text":"Absolute axis: chunk 11374..11405 cycles, 45498.000..45622.000 ns"}}